top.sv
module top (
    input clk
);

    // TODO: Setup to be dealt with later
    parameter S_FETCH   = 3'b000;
    parameter S_DECODE  = 3'b001;
    parameter S_EXECUTE = 3'b010;
    parameter S_MEMACC  = 3'b011;
    parameter S_WRTBCK  = 3'b100;

    reg [2:0] state = S_FETCH;

    reg [31:0] mem [0:1023];
    // TODO: THIS CANNOT BE A REG, IT MUST BE CONNECTED THROUGH AN ADDRESS BUS

    // Main registers
    reg [31:0] reg_file [0:31];
    reg [31:0] pc;

    // ----------- Pipeline registers -----------
    // FETCH
    reg [31:0] instruction;

    // DECODE
    reg [6:0] opcode;
    reg [4:0] rs1;
    reg [4:0] rs2;
    reg [4:0] rd;
    reg [2:0] funct3;
    reg [6:0] funct7;
    reg [31:0] imm;

    // EXECUTE
    reg [31:0] rd_data;

    // MEMACC
    reg [31:0] mem_addr;

    // WRTBCK
    reg [31:0] mem_out;
    reg [31:0] jmp_addr;

    initial begin
        pc <= 0;
        for (int i = 0; i < 32; i = i + 1) reg_file[i] <= 0;
        mem[0]  <= 32'b00000000000100000000000010010011; // ADDI R1, R0, 1
        mem[4]  <= 32'b00000000000100000000000100010011; // ADDI R2, R0, 1
        mem[8]  <= 32'b00000110010000000000000110010011; // ADDI R3, R0, 100
        mem[12] <= 32'b00000000000100010000000010110011; // ADD R1, R1, R2
        mem[16] <= 32'b00000000000100011010000000100011; // SW R1, 0(R3)
        mem[20] <= 32'b00000000000100010000000100110011; // ADD R2, R1, R2
        mem[24] <= 32'b00000000001000011010000010100011; // SW R2, 0(R3)
        mem[28] <= 32'b00000000001000011000000110010011; // ADDI R3, R3, 1
        mem[32] <= 32'b00000000110000000000000001100111; // JALR, R0, R0, 8
    end

    // ----------- Pipeline Logic -----------
    always @ (posedge clk) begin
        // dump info
        case (state)
            S_FETCH: begin
                instruction <= mem[pc];
                pc <= pc + 4;
                state <= S_DECODE;
            end
            S_DECODE: begin
                opcode <= instruction[6:0];
                rs1    <= instruction[19:15];
                rs2    <= instruction[24:20];
                rd     <= instruction[11:7];
                funct3 <= instruction[14:12];
                funct7 <= instruction[31:25];
                case (instruction[6:0])
                    7'b0110111, 7'b0010111: imm <= {instruction[31:12], 12'b0}; // U-type
                    7'b1101111: imm <= {{13{instruction[31]}}, instruction[19:12], instruction[20], instruction[30:21], 1'b0}; // J-type
                    7'b1100111, 7'b0000011, 7'b0010011: imm <= {{20{instruction[31]}}, instruction[31:20]}; // I-type
                    7'b1100011: imm <= {instruction[31], instruction[7], instruction[30:25], instruction[11:8], 1'b0}; // B-type
                    7'b0100011: imm <= {instruction[31:25], instruction[11:7]}; // S-type
                endcase
                state <= S_EXECUTE;
            end
            S_EXECUTE: begin
                case (opcode)
                    7'b0110111: rd_data <= imm; // LUI
                    7'b0010111: rd_data <= imm + pc; // AUIPC
                    7'b1101111: begin // JAL
                        jmp_addr <= pc + imm;
                        rd_data <= pc + 4;
                    end
                    7'b1100111: begin // JALR
                        jmp_addr <= reg_file[rs1] + imm;
                        jmp_addr[0] <= 1'b0;
                        rd_data <= pc + 4;
                    end
                    7'b1100011: begin // BRANCH
                        jmp_addr <= pc + 4; // If not jumping, return to next instruction
                        case (funct3)
                            3'b000: begin // BEQ
                                if (reg_file[rs1] == reg_file[rs2]) begin
                                    jmp_addr <= pc + imm;
                                    jmp_addr[0] <= 1'b0;
                                end
                            end
                            3'b001: begin // BNE
                                if (reg_file[rs1] != reg_file[rs2]) begin
                                    jmp_addr <= pc + imm;
                                    jmp_addr[0] <= 1'b0;
                                end
                            end
                            3'b100: begin // BLT
                                if (reg_file[rs1] < reg_file[rs2]) begin
                                    jmp_addr <= pc + imm;
                                    jmp_addr[0] <= 1'b0;
                                end
                            end
                            3'b101: begin // BGE
                                if (reg_file[rs1] >= reg_file[rs2]) begin
                                    jmp_addr <= pc + imm;
                                    jmp_addr[0] <= 1'b0;
                                end
                            end
                            3'b110: begin // BLTU
                                if (reg_file[rs1] < reg_file[rs2]) begin
                                    jmp_addr <= pc + imm;
                                    jmp_addr[0] <= 1'b0;
                                end
                            end
                            3'b111: begin // BGEU
                                if (reg_file[rs1] >= reg_file[rs2]) begin
                                    jmp_addr <= pc + imm;
                                    jmp_addr[0] <= 1'b0;
                                end
                            end
                        endcase
                    end
                    7'b0000011: begin
                        case (funct3)
                            3'b000: mem_addr <= reg_file[rs1] + imm; // LB
                            3'b001: mem_addr <= reg_file[rs1] + imm; // LH
                            3'b010: mem_addr <= reg_file[rs1] + imm; // LW
                            3'b100: mem_addr <= reg_file[rs1] + imm; // LBU
                            3'b101: mem_addr <= reg_file[rs1] + imm; // LHU
                        endcase
                    end
                    7'b0100011: begin
                        mem_addr <= reg_file[rs1] + imm;
                        case (funct3)
                            3'b000: mem_out <= reg_file[rs2][7:0]; // SB
                            3'b001: mem_out <= reg_file[rs2][15:0]; // SH
                            3'b010: mem_out <= reg_file[rs2][31:0]; // SW
                        endcase
                    end
                    7'b0010011: begin
                        case (funct3)
                            3'b000: rd_data <= reg_file[rs1] + imm; // ADDI
                            3'b010: rd_data <= reg_file[rs1] < imm; // SLTI
                            3'b011: rd_data <= reg_file[rs1] < imm; // SLTIU
                            3'b100: rd_data <= reg_file[rs1] ^ imm; // XORI
                            3'b110: rd_data <= reg_file[rs1] | imm; // ORI
                            3'b111: rd_data <= reg_file[rs1] & imm; // ANDI
                            3'b001: rd_data <= reg_file[rs1] << imm[4:0]; // SLLI
                            3'b101: begin // SRLI/SRAI
                                if (funct7[5] == 1'b0) begin
                                    rd_data <= reg_file[rs1] >> imm[4:0]; // SRLI
                                end else begin
                                    // TODO: rd_data <= {imm[4:0], reg_file[rs1][31:imm[4:0]]}; // SRAI
                                end
                            end
                        endcase
                    end
                    7'b0110011: begin
                        case (funct3)
                            3'b000: begin // ADD/SUB
                                if (funct7 == 7'b0000000) begin
                                    rd_data <= reg_file[rs1] + reg_file[rs2]; // ADD
                                end else begin
                                    rd_data <= reg_file[rs1] - reg_file[rs2]; // SUB
                                end
                            end
                            3'b001: rd_data <= reg_file[rs1] << reg_file[rs2]; // SLL
                            3'b010: rd_data <= reg_file[rs1] < reg_file[rs2]; // SLT
                            3'b011: rd_data <= reg_file[rs1] < reg_file[rs2]; // SLTU
                            3'b100: rd_data <= reg_file[rs1] ^ reg_file[rs2]; // XOR
                            3'b101: begin // SRL/SRA
                                if (funct7 == 7'b0000000) begin
                                    rd_data <= reg_file[rs1] >> reg_file[rs2]; // SRL
                                end else begin
                                    //TODO: rd_data <= {reg_file[rs1][31:0], reg_file[rs1][31:reg_file[rs2]]}; // SRA
                                end
                            end
                            3'b110: rd_data <= reg_file[rs1] | reg_file[rs2]; // OR
                            3'b111: rd_data <= reg_file[rs1] & reg_file[rs2]; // AND
                        endcase
                    end
                    default: begin end
                endcase
                state <= S_MEMACC;
            end
            S_MEMACC: begin
                // TODO: For now this is empty
                state <= S_WRTBCK;
            end
            S_WRTBCK: begin
                $display("Arrived at WRTBCK");
                case (opcode)
                    7'b0110111, 7'b0010111, 7'b0000011, 7'b0010011, 7'b0110011: begin
                        $display("Writing %h to register %d", rd_data, rd);
                        if (rd != 0) reg_file[rd] <= rd_data;
                    end
                    7'b1100011, 7'b0000011, 7'b0100011: begin
                        $display("Writing %h to memory address %d", mem_out, mem_addr);
                        mem[mem_addr] <= mem_out;
                    end
                    7'b1101111, 7'b1100111, 7'b1100011: begin
                        $display("JUMPIIIIIIIIIIIIIIIIIIING");
                        pc <= jmp_addr; // TODO: Check if this is correct, maybe move this part to the execute stage to save some time
                    end
                    default: begin end
                endcase
                state <= S_FETCH;
                $display("Jump Address: %b", jmp_addr);
                $display("State: %b", state);
                $display("PC: %d", pc);
                $display("Instruction: %b", instruction);
                $display("Opcode: %b", opcode);
                $display("RS1: %b", rs1);
                $display("RS2: %b", rs2);
                $display("RD: %b", rd);
                $display("Funct3: %b", funct3);
                $display("Funct7: %b", funct7);
                $display("Imm: %b", imm);
                $display("R1: %h", reg_file[1]);
                $display("R2: %h", reg_file[2]);
                $display("R3: %h", reg_file[3]);
                $display("R4: %h", reg_file[4]);
                $display("R5: %h", reg_file[5]);
                $display("R6: %h", reg_file[6]);
                $display("R7: %h", reg_file[7]);
                $display("R8: %h", reg_file[8]);
                $display("R9: %h", reg_file[9]);
                $display("ADDR-100: %h", mem[100]);
                $display("ADDR-101: %h", mem[101]);
                $display("ADDR-102: %h", mem[102]);
                $display("ADDR-103: %h", mem[103]);
                $display("ADDR-104: %h", mem[104]);
                $display("----------------------------------------------------");
            end
        endcase
    end

endmodule : top

testbench.sv
module tb;
    reg clk;
    top PROCESSOR(clk);
    initial begin
        clk = 0;
        #1000 $finish;
    end
    always #5 clk = ~clk;
endmodule : tb

dump.vcd
$date
	Wed Sep 13 19:21:36 2023
$end
$version
	Icarus Verilog
$end
$timescale
	1s
$end
$scope module tb $end
$var reg 1 ! clk $end
$scope module PROCESSOR $end
$var wire 1 ! clk $end
$var reg 3 " funct3 [2:0] $end
$var reg 7 # funct7 [6:0] $end
$var reg 32 $ imm [31:0] $end
$var reg 32 % instruction [31:0] $end
$var reg 32 & jmp_addr [31:0] $end
$var reg 32 ' mem_addr [31:0] $end
$var reg 32 ( mem_out [31:0] $end
$var reg 7 ) opcode [6:0] $end
$var reg 32 * pc [31:0] $end
$var reg 5 + rd [4:0] $end
$var reg 32 , rd_data [31:0] $end
$var reg 5 - rs1 [4:0] $end
$var reg 5 . rs2 [4:0] $end
$var reg 3 / state [2:0] $end
$scope begin $ivl_for_loop0 $end
$var integer 32 0 i [31:0] $end
$upscope $end
$upscope $end
$upscope $end
$enddefinitions $end
#0
$dumpvars
b100000 0
b0 /
bx .
bx -
bx ,
bx +
b0 *
bx )
bx (
bx '
bx &
bx %
bx $
bx #
bx "
0!
$end
#5
b1 /
b100 *
b100000000000010010011 %
1!
#10
0!
#15
b10 /
b1 $
b0 #
b0 "
b1 +
b1 .
b0 -
b10011 )
1!
#20
0!
#25
b11 /
b1 ,
1!
#30
0!
#35
b100 /
1!
#40
0!
#45
b0 /
1!
#50
0!
#55
b1 /
b1000 *
b100000000000100010011 %
1!
#60
0!
#65
b10 /
b10 +
1!
#70
0!
#75
b11 /
1!
#80
0!
#85
b100 /
1!
#90
0!
#95
b0 /
1!
#100
0!
#105
b1 /
b1100 *
b110010000000000000110010011 %
1!
#110
0!
#115
b10 /
b1100100 $
b11 #
b11 +
b100 .
1!
#120
0!
#125
b11 /
b1100100 ,
1!
#130
0!
#135
b100 /
1!
#140
0!
#145
b0 /
1!
#150
0!
#155
b1 /
b10000 *
b100010000000010110011 %
1!
#160
0!
#165
b10 /
b0 #
b1 +
b1 .
b10 -
b110011 )
1!
#170
0!
#175
b11 /
b10 ,
1!
#180
0!
#185
b100 /
1!
#190
0!
#195
b0 /
1!
#200
0!
#205
b1 /
b10100 *
b100011010000000100011 %
1!
#210
0!
#215
b10 /
b0 $
b10 "
b0 +
b11 -
b100011 )
1!
#220
0!
#225
b11 /
b10 (
b1100100 '
1!
#230
0!
#235
b100 /
1!
#240
0!
#245
b0 /
1!
#250
0!
#255
b1 /
b11000 *
b100010000000100110011 %
1!
#260
0!
#265
b10 /
b0 "
b10 +
b10 -
b110011 )
1!
#270
0!
#275
b11 /
b11 ,
1!
#280
0!
#285
b100 /
1!
#290
0!
#295
b0 /
1!
#300
0!
#305
b1 /
b11100 *
b1000011010000010100011 %
1!
#310
0!
#315
b10 /
b1 $
b10 "
b1 +
b10 .
b11 -
b100011 )
1!
#320
0!
#325
b11 /
b11 (
b1100101 '
1!
#330
0!
#335
b100 /
1!
#340
0!
#345
b0 /
1!
#350
0!
#355
b1 /
b100000 *
b1000011000000110010011 %
1!
#360
0!
#365
b10 /
b10 $
b0 "
b11 +
b10011 )
1!
#370
0!
#375
b11 /
b1100110 ,
1!
#380
0!
#385
b100 /
1!
#390
0!
#395
b0 /
1!
#400
0!
#405
b1 /
b100100 *
b110000000000000001100111 %
1!
#410
0!
#415
b10 /
b1100 $
b0 +
b1100 .
b0 -
b1100111 )
1!
#420
0!
#425
b11 /
b101000 ,
b1100 &
1!
#430
0!
#435
b100 /
1!
#440
0!
#445
b0 /
b1100 *
1!
#450
0!
#455
b1 /
b10000 *
b100010000000010110011 %
1!
#460
0!
#465
b10 /
b1 +
b1 .
b10 -
b110011 )
1!
#470
0!
#475
b11 /
b101 ,
1!
#480
0!
#485
b100 /
1!
#490
0!
#495
b0 /
1!
#500
0!
#505
b1 /
b10100 *
b100011010000000100011 %
1!
#510
0!
#515
b10 /
b0 $
b10 "
b0 +
b11 -
b100011 )
1!
#520
0!
#525
b11 /
b101 (
b1100110 '
1!
#530
0!
#535
b100 /
1!
#540
0!
#545
b0 /
1!
#550
0!
#555
b1 /
b11000 *
b100010000000100110011 %
1!
#560
0!
#565
b10 /
b0 "
b10 +
b10 -
b110011 )
1!
#570
0!
#575
b11 /
b1000 ,
1!
#580
0!
#585
b100 /
1!
#590
0!
#595
b0 /
1!
#600
0!
#605
b1 /
b11100 *
b1000011010000010100011 %
1!
#610
0!
#615
b10 /
b1 $
b10 "
b1 +
b10 .
b11 -
b100011 )
1!
#620
0!
#625
b11 /
b1000 (
b1100111 '
1!
#630
0!
#635
b100 /
1!
#640
0!
#645
b0 /
1!
#650
0!
#655
b1 /
b100000 *
b1000011000000110010011 %
1!
#660
0!
#665
b10 /
b10 $
b0 "
b11 +
b10011 )
1!
#670
0!
#675
b11 /
b1101000 ,
1!
#680
0!
#685
b100 /
1!
#690
0!
#695
b0 /
1!
#700
0!
#705
b1 /
b100100 *
b110000000000000001100111 %
1!
#710
0!
#715
b10 /
b1100 $
b0 +
b1100 .
b0 -
b1100111 )
1!
#720
0!
#725
b11 /
b101000 ,
1!
#730
0!
#735
b100 /
1!
#740
0!
#745
b0 /
b1100 *
1!
#750
0!
#755
b1 /
b10000 *
b100010000000010110011 %
1!
#760
0!
#765
b10 /
b1 +
b1 .
b10 -
b110011 )
1!
#770
0!
#775
b11 /
b1101 ,
1!
#780
0!
#785
b100 /
1!
#790
0!
#795
b0 /
1!
#800
0!
#805
b1 /
b10100 *
b100011010000000100011 %
1!
#810
0!
#815
b10 /
b0 $
b10 "
b0 +
b11 -
b100011 )
1!
#820
0!
#825
b11 /
b1101 (
b1101000 '
1!
#830
0!
#835
b100 /
1!
#840
0!
#845
b0 /
1!
#850
0!
#855
b1 /
b11000 *
b100010000000100110011 %
1!
#860
0!
#865
b10 /
b0 "
b10 +
b10 -
b110011 )
1!
#870
0!
#875
b11 /
b10101 ,
1!
#880
0!
#885
b100 /
1!
#890
0!
#895
b0 /
1!
#900
0!
#905
b1 /
b11100 *
b1000011010000010100011 %
1!
#910
0!
#915
b10 /
b1 $
b10 "
b1 +
b10 .
b11 -
b100011 )
1!
#920
0!
#925
b11 /
b10101 (
b1101001 '
1!
#930
0!
#935
b100 /
1!
#940
0!
#945
b0 /
1!
#950
0!
#955
b1 /
b100000 *
b1000011000000110010011 %
1!
#960
0!
#965
b10 /
b10 $
b0 "
b11 +
b10011 )
1!
#970
0!
#975
b11 /
b1101010 ,
1!
#980
0!
#985
b100 /
1!
#990
0!
#995
b0 /
1!
